{"counties":["Appling","Atkinson","Bacon","Baker","Baldwin","Banks","Barrow","Bartow","Ben Hill","Berrien","Bibb","Bleckley","Brantley","Brooks","Bryan","Bulloch","Burke","Butts","Calhoun","Camden","Candler","Carroll","Catoosa","Charlton","Chatham","Chattahoochee","Chattooga","Cherokee","Clarke","Clay","Clayton","Clinch","Cobb","Coffee","Colquitt","Columbia","Cook","Coweta","Crawford","Crisp","Dade","Dawson","Decatur","Dekalb","Dodge","Dooly","Dougherty","Douglas","Early","Echols","Effingham","Elbert","Emanuel","Evans","Fannin","Fayette","Floyd","Forsyth","Franklin","Fulton","Gilmer","Glascock","Glynn","Gordon","Grady","Greene","Gwinnett","Habersham","Hall","Hancock","Haralson","Harris","Hart","Heard","Henry","Houston","Irwin","Jackson","Jasper","Jeff Davis","Jefferson","Jenkins","Johnson","Jones","Lamar","Lanier","Laurens","Lee","Liberty","Lincoln","Long","Lowndes","Lumpkin","Macon","Madison","Marion","Mcduffie","Mcintosh","Meriwether","Miller","Mitchell","Monroe","Montgomery","Morgan","Murray","Muscogee","Newton","Oconee","Oglethorpe","Paulding","Peach","Pickens","Pierce","Pike","Polk","Pulaski","Putnam","Quitman","Rabun","Randolph","Richmond","Rockdale","Schley","Screven","Seminole","Spalding","Stephens","Stewart","Sumter","Talbot","Taliaferro","Tattnall","Taylor","Telfair","Terrell","Thomas","Tift","Toombs","Towns","Treutlen","Troup","Turner","Twiggs","Union","Upson","Walker","Walton","Ware","Warren","Washington","Wayne","Webster","Wheeler","White","Whitfield","Wilcox","Wilkes","Wilkinson","Worth"],"cities":[{"n":"Abbeville","c":"Wilcox","z":["31001"],"lat":31.977,"lng":-83.3725},{"n":"Acworth","c":"Cobb","z":["30101","30102"],"lat":34.0234,"lng":-84.6738},{"n":"Adairsville","c":"Bartow","z":["30103"],"lat":34.2963,"lng":-84.9092},{"n":"Adel","c":"Cook","z":["31620"],"lat":31.1517,"lng":-83.4071},{"n":"Adrian","c":"Emanuel","z":["31002"],"lat":32.5689,"lng":-82.5403},{"n":"Ailey","c":"Montgomery","z":["30410"],"lat":32.1797,"lng":-82.5166},{"n":"Alamo","c":"Wheeler","z":["30411"],"lat":32.143,"lng":-82.8268},{"n":"Alapaha","c":"Berrien","z":["31622"],"lat":31.384,"lng":-83.2213},{"n":"Albany","c":"Dougherty","z":["31701","31702","31703","31704","31705","31706","31707","31708"],"lat":31.5607,"lng":-84.1768},{"n":"Allenhurst","c":"Liberty","z":["31301"],"lat":31.7791,"lng":-81.6038},{"n":"Allentown","c":"Wilkinson","z":["31003"],"lat":32.6064,"lng":-83.2095},{"n":"Alma","c":"Bacon","z":["31510"],"lat":31.577,"lng":-82.4612},{"n":"Alpharetta","c":"Fulton","z":["30004","30005","30009","30022","30023"],"lat":34.1124,"lng":-84.302},{"n":"Alston","c":"Montgomery","z":["30412"],"lat":32.0775,"lng":-82.4825},{"n":"Alto","c":"Habersham","z":["30510","30596"],"lat":34.5043,"lng":-83.5948},{"n":"Ambrose","c":"Coffee","z":["31512"],"lat":31.5496,"lng":-82.9873},{"n":"Americus","c":"Sumter","z":["31709","31710"],"lat":32.0404,"lng":-84.2153},{"n":"Andersonville","c":"Sumter","z":["31711"],"lat":32.1559,"lng":-84.164},{"n":"Appling","c":"Columbia","z":["30802"],"lat":33.574,"lng":-82.3121},{"n":"Arabi","c":"Crisp","z":["31712"],"lat":31.8496,"lng":-83.7277},{"n":"Aragon","c":"Polk","z":["30104"],"lat":34.0532,"lng":-85.0799},{"n":"Argyle","c":"Clinch","z":["31623"],"lat":31.0641,"lng":-82.6895},{"n":"Arlington","c":"Calhoun","z":["31713"],"lat":31.4772,"lng":-84.6992},{"n":"Armuchee","c":"Floyd","z":["30105"],"lat":34.4793,"lng":-85.1492},{"n":"Arnoldsville","c":"Oglethorpe","z":["30619"],"lat":33.8887,"lng":-83.2223},{"n":"Ashburn","c":"Turner","z":["31714"],"lat":31.7231,"lng":-83.6441},{"n":"Athens","c":"Clarke","z":["30601","30602","30603","30604","30605","30606","30607","30608","30609","30612"],"lat":33.9929,"lng":-83.3537},{"n":"Atlanta","c":"Fulton","z":["30301","30302","30303","30304","30305","30306","30307","30308","30309","30310","30311","30312","30313","30314","30315","30316","30317","30318","30320","30321","30324","30325","30326","30327","30328","30330","30331","30332","30334","30336","30337","30338","30339","30342","30343","30344","30347","30348","30349","30353","30354","30355","30357","30358","30361","30364","30368","30369","30370","30371","30374","30375","30376","30377","30378","30379","30380","30384","30385","30386","30387","30388","30389","30390","30392","30394","30396","30398","30399","31106","31107","31126","31131","31139","31150","31156","31191","31192","31193","31195","31196","31197","31198","31199"],"lat":33.8444,"lng":-84.4741},{"n":"Atlanta","c":"Dekalb","z":["30319","30322","30329","30333","30340","30341","30345","30346","30350","30356","30359","30360","30362","30366","31119","31141","31145","31146","39901"],"lat":33.8768,"lng":-84.3291},{"n":"Attapulgus","c":"Decatur","z":["31715"],"lat":30.8353,"lng":-84.5119},{"n":"Auburn","c":"Barrow","z":["30011"],"lat":34.0191,"lng":-83.8261},{"n":"Augusta","c":"Richmond","z":["30901","30903","30904","30905","30906","30907","30909","30910","30911","30912","30913","30914","30916","30919","30999"],"lat":33.4567,"lng":-81.9692},{"n":"Augusta","c":"Columbia","z":["30917"],"lat":33.5277,"lng":-82.2355},{"n":"Austell","c":"Cobb","z":["30106","30168"],"lat":33.8369,"lng":-84.6307},{"n":"Avera","c":"Jefferson","z":["30803"],"lat":33.1413,"lng":-82.527},{"n":"Avondale Estates","c":"Dekalb","z":["30002"],"lat":33.7717,"lng":-84.2394},{"n":"Axson","c":"Atkinson","z":["31624"],"lat":31.3032,"lng":-82.848},{"n":"Baconton","c":"Mitchell","z":["31716"],"lat":31.3589,"lng":-84.1003},{"n":"Bainbridge","c":"Decatur","z":["31717","31718"],"lat":30.8887,"lng":-84.6178},{"n":"Baldwin","c":"Banks","z":["30511"],"lat":34.3937,"lng":-83.4739},{"n":"Ball Ground","c":"Cherokee","z":["30107"],"lat":34.3012,"lng":-84.4429},{"n":"Barnesville","c":"Lamar","z":["30204"],"lat":33.0758,"lng":-84.1457},{"n":"Barney","c":"Brooks","z":["31625"],"lat":30.8566,"lng":-83.5265},{"n":"Bartow","c":"Jefferson","z":["30413"],"lat":32.8891,"lng":-82.4666},{"n":"Barwick","c":"Brooks","z":["31720"],"lat":30.8566,"lng":-83.5265},{"n":"Baxley","c":"Appling","z":["31513","31515"],"lat":31.7569,"lng":-82.3508},{"n":"Bellville","c":"Evans","z":["30414"],"lat":32.1634,"lng":-81.8719},{"n":"Berlin","c":"Colquitt","z":["31722"],"lat":31.0807,"lng":-83.6491},{"n":"Bethlehem","c":"Barrow","z":["30620"],"lat":33.9437,"lng":-83.7215},{"n":"Bishop","c":"Oconee","z":["30621"],"lat":33.8057,"lng":-83.4817},{"n":"Blackshear","c":"Pierce","z":["31516"],"lat":31.3263,"lng":-82.2712},{"n":"Blairsville","c":"Union","z":["30512","30514"],"lat":34.8675,"lng":-83.9676},{"n":"Blakely","c":"Early","z":["31723"],"lat":31.3461,"lng":-84.9012},{"n":"Bloomingdale","c":"Chatham","z":["31302"],"lat":32.1071,"lng":-81.2913},{"n":"Blue Ridge","c":"Fannin","z":["30513"],"lat":34.8312,"lng":-84.3313},{"n":"Bluffton","c":"Clay","z":["31724"],"lat":31.5575,"lng":-84.8542},{"n":"Blythe","c":"Richmond","z":["30805"],"lat":33.3597,"lng":-82.1989},{"n":"Bogart","c":"Oconee","z":["30622"],"lat":33.902,"lng":-83.5185},{"n":"Bolingbroke","c":"Monroe","z":["31004"],"lat":32.947,"lng":-83.8006},{"n":"Bonaire","c":"Houston","z":["31005"],"lat":32.5395,"lng":-83.6627},{"n":"Boneville","c":"Mcduffie","z":["30806"],"lat":33.528,"lng":-82.5104},{"n":"Boston","c":"Thomas","z":["31626"],"lat":30.8286,"lng":-83.911},{"n":"Bostwick","c":"Morgan","z":["30623"],"lat":33.7542,"lng":-83.5111},{"n":"Bowdon","c":"Carroll","z":["30108"],"lat":33.5877,"lng":-85.1239},{"n":"Bowdon Junction","c":"Carroll","z":["30109"],"lat":33.6534,"lng":-85.1362},{"n":"Bowersville","c":"Hart","z":["30516"],"lat":34.384,"lng":-83.0332},{"n":"Bowman","c":"Elbert","z":["30624"],"lat":34.1641,"lng":-82.9571},{"n":"Box Springs","c":"Talbot","z":["31801"],"lat":32.7011,"lng":-84.4949},{"n":"Braselton","c":"Jackson","z":["30517"],"lat":34.1099,"lng":-83.6851},{"n":"Bremen","c":"Haralson","z":["30110"],"lat":33.768,"lng":-85.1729},{"n":"Brinson","c":"Decatur","z":["31725"],"lat":30.9079,"lng":-84.7038},{"n":"Bristol","c":"Pierce","z":["31518"],"lat":31.4833,"lng":-82.215},{"n":"Bronwood","c":"Terrell","z":["31726"],"lat":31.824,"lng":-84.3432},{"n":"Brookfield","c":"Tift","z":["31727"],"lat":31.4417,"lng":-83.5037},{"n":"Brooklet","c":"Bulloch","z":["30415"],"lat":32.3523,"lng":-81.6571},{"n":"Brooks","c":"Fayette","z":["30205"],"lat":33.3001,"lng":-84.4532},{"n":"Broxton","c":"Coffee","z":["31519"],"lat":31.6719,"lng":-82.8649},{"n":"Brunswick","c":"Glynn","z":["31520","31521","31523","31524","31525"],"lat":31.2304,"lng":-81.4929},{"n":"Buchanan","c":"Haralson","z":["30113"],"lat":33.8367,"lng":-85.2104},{"n":"Buckhead","c":"Morgan","z":["30625"],"lat":33.5256,"lng":-83.3656},{"n":"Buena Vista","c":"Marion","z":["31803"],"lat":32.2542,"lng":-84.4898},{"n":"Buford","c":"Gwinnett","z":["30515","30518","30519"],"lat":33.9604,"lng":-84.0379},{"n":"Butler","c":"Taylor","z":["31006"],"lat":32.5727,"lng":-84.2261},{"n":"Byromville","c":"Dooly","z":["31007"],"lat":32.1858,"lng":-83.9014},{"n":"Byron","c":"Peach","z":["31008"],"lat":32.6181,"lng":-83.789},{"n":"Cadwell","c":"Laurens","z":["31009"],"lat":32.3039,"lng":-83.0094},{"n":"Cairo","c":"Grady","z":["31728"],"lat":30.8575,"lng":-84.229},{"n":"Calhoun","c":"Gordon","z":["30701","30703"],"lat":34.4969,"lng":-84.8879},{"n":"Calvary","c":"Grady","z":["31729"],"lat":30.7147,"lng":-84.3518},{"n":"Camak","c":"Warren","z":["30807"],"lat":33.4471,"lng":-82.6422},{"n":"Camilla","c":"Mitchell","z":["31730"],"lat":31.2492,"lng":-84.2428},{"n":"Canon","c":"Franklin","z":["30520"],"lat":34.3559,"lng":-83.1529},{"n":"Canton","c":"Cherokee","z":["30114","30115"],"lat":34.2505,"lng":-84.4909},{"n":"Carlton","c":"Madison","z":["30627"],"lat":34.0592,"lng":-83.0993},{"n":"Carnesville","c":"Franklin","z":["30521"],"lat":34.3631,"lng":-83.2547},{"n":"Carrollton","c":"Carroll","z":["30116","30117","30118","30119"],"lat":33.6045,"lng":-85.0499},{"n":"Cartersville","c":"Bartow","z":["30120","30121"],"lat":34.2008,"lng":-84.8471},{"n":"Cassville","c":"Bartow","z":["30123"],"lat":34.2442,"lng":-84.8457},{"n":"Cataula","c":"Harris","z":["31804"],"lat":32.6616,"lng":-84.8554},{"n":"Cave Spring","c":"Floyd","z":["30124"],"lat":34.1616,"lng":-85.3328},{"n":"Cecil","c":"Cook","z":["31627"],"lat":31.0403,"lng":-83.3915},{"n":"Cedar Springs","c":"Early","z":["31732"],"lat":31.2956,"lng":-84.8711},{"n":"Cedartown","c":"Polk","z":["30125"],"lat":33.9988,"lng":-85.2394},{"n":"Centerville","c":"Houston","z":["31028"],"lat":32.5682,"lng":-83.7018},{"n":"Chatsworth","c":"Murray","z":["30705"],"lat":34.7855,"lng":-84.7716},{"n":"Chauncey","c":"Dodge","z":["31011"],"lat":32.1504,"lng":-83.0555},{"n":"Cherrylog","c":"Gilmer","z":["30522"],"lat":34.7325,"lng":-84.425},{"n":"Chester","c":"Dodge","z":["31012"],"lat":32.3106,"lng":-83.1609},{"n":"Chestnut Mountain","c":"Hall","z":["30502"],"lat":34.213,"lng":-83.7949},{"n":"Chickamauga","c":"Walker","z":["30707"],"lat":34.7642,"lng":-85.3535},{"n":"Chula","c":"Tift","z":["31733"],"lat":31.5575,"lng":-83.5094},{"n":"Cisco","c":"Murray","z":["30708"],"lat":34.8725,"lng":-84.7569},{"n":"Clarkdale","c":"Cobb","z":["30111"],"lat":33.9125,"lng":-84.5572},{"n":"Clarkesville","c":"Habersham","z":["30523"],"lat":34.6559,"lng":-83.5083},{"n":"Clarkston","c":"Dekalb","z":["30021"],"lat":33.811,"lng":-84.238},{"n":"Claxton","c":"Evans","z":["30417"],"lat":32.1606,"lng":-81.9238},{"n":"Clayton","c":"Rabun","z":["30525"],"lat":34.8869,"lng":-83.3754},{"n":"Clermont","c":"Hall","z":["30527"],"lat":34.3978,"lng":-83.7757},{"n":"Cleveland","c":"White","z":["30528"],"lat":34.6105,"lng":-83.7462},{"n":"Climax","c":"Decatur","z":["31734"],"lat":30.8873,"lng":-84.4683},{"n":"Clinchfield","c":"Houston","z":["31013"],"lat":32.3386,"lng":-83.6926},{"n":"Clyo","c":"Effingham","z":["31303"],"lat":32.488,"lng":-81.3224},{"n":"Cobb","c":"Sumter","z":["31735"],"lat":31.9684,"lng":-83.979},{"n":"Cobbtown","c":"Tattnall","z":["30420"],"lat":32.106,"lng":-82.0339},{"n":"Cochran","c":"Bleckley","z":["31014"],"lat":32.3839,"lng":-83.3211},{"n":"Cohutta","c":"Whitfield","z":["30710"],"lat":34.8678,"lng":-84.9195},{"n":"Colbert","c":"Madison","z":["30628"],"lat":34.0882,"lng":-83.2024},{"n":"Coleman","c":"Randolph","z":["31736"],"lat":31.7752,"lng":-84.7472},{"n":"Collins","c":"Tattnall","z":["30421"],"lat":32.0586,"lng":-82.0274},{"n":"Colquitt","c":"Miller","z":["31737"],"lat":31.1625,"lng":-84.7134},{"n":"Columbus","c":"Muscogee","z":["31901","31902","31903","31904","31906","31907","31908","31909","31914","31917","31993","31994","31997","31998","31999"],"lat":32.4729,"lng":-84.9782},{"n":"Comer","c":"Madison","z":["30629"],"lat":34.1057,"lng":-83.1445},{"n":"Commerce","c":"Jackson","z":["30529","30530","30599"],"lat":34.1697,"lng":-83.5707},{"n":"Concord","c":"Pike","z":["30206"],"lat":33.1047,"lng":-84.4569},{"n":"Conley","c":"Dekalb","z":["30288"],"lat":33.6369,"lng":-84.3371},{"n":"Conyers","c":"Rockdale","z":["30012","30013","30094"],"lat":33.7192,"lng":-84.0021},{"n":"Coolidge","c":"Thomas","z":["31738"],"lat":30.9763,"lng":-83.8713},{"n":"Coosa","c":"Floyd","z":["30129"],"lat":34.3333,"lng":-85.2337},{"n":"Cordele","c":"Crisp","z":["31010","31015"],"lat":31.9172,"lng":-83.7854},{"n":"Cornelia","c":"Habersham","z":["30531"],"lat":34.5352,"lng":-83.574},{"n":"Cotton","c":"Mitchell","z":["31739"],"lat":31.2604,"lng":-84.2531},{"n":"Covington","c":"Newton","z":["30014","30015","30016"],"lat":33.5293,"lng":-83.8496},{"n":"Crandall","c":"Murray","z":["30711"],"lat":34.8876,"lng":-84.7446},{"n":"Crawford","c":"Oglethorpe","z":["30630"],"lat":33.9076,"lng":-83.1646},{"n":"Crawfordville","c":"Taliaferro","z":["30631"],"lat":33.577,"lng":-82.8581},{"n":"Crescent","c":"Mcintosh","z":["31304"],"lat":31.4951,"lng":-81.3819},{"n":"Culloden","c":"Monroe","z":["31016"],"lat":32.9003,"lng":-84.0626},{"n":"Cumming","c":"Forsyth","z":["30028","30040","30041"],"lat":34.193,"lng":-84.0926},{"n":"Cusseta","c":"Chattahoochee","z":["31805"],"lat":32.2925,"lng":-84.7367},{"n":"Cuthbert","c":"Randolph","z":["31740"],"lat":31.7312,"lng":-84.8322},{"n":"Dacula","c":"Gwinnett","z":["30019"],"lat":33.9883,"lng":-83.8795},{"n":"Dahlonega","c":"Lumpkin","z":["30533","30597"],"lat":34.5414,"lng":-84.0244},{"n":"Daisy","c":"Evans","z":["30423"],"lat":32.1634,"lng":-81.8719},{"n":"Dallas","c":"Paulding","z":["30132","30157"],"lat":33.9354,"lng":-84.8667},{"n":"Dalton","c":"Whitfield","z":["30719","30720","30721","30722"],"lat":34.8019,"lng":-84.9898},{"n":"Damascus","c":"Early","z":["31741"],"lat":31.2981,"lng":-84.7175},{"n":"Danielsville","c":"Madison","z":["30633"],"lat":34.153,"lng":-83.2628},{"n":"Danville","c":"Twiggs","z":["31017"],"lat":32.6077,"lng":-83.2691},{"n":"Darien","c":"Mcintosh","z":["31305"],"lat":31.4138,"lng":-81.3693},{"n":"Davisboro","c":"Washington","z":["31018"],"lat":32.9684,"lng":-82.6484},{"n":"Dawson","c":"Terrell","z":["31742"],"lat":31.7661,"lng":-84.4386},{"n":"Dawsonville","c":"Dawson","z":["30534"],"lat":34.4537,"lng":-84.155},{"n":"De Soto","c":"Sumter","z":["31743"],"lat":31.9381,"lng":-84.031},{"n":"Dearing","c":"Mcduffie","z":["30808"],"lat":33.4044,"lng":-82.4016},{"n":"Decatur","c":"Dekalb","z":["30030","30031","30032","30033","30034","30035","30036","30037"],"lat":33.7726,"lng":-84.2917},{"n":"Demorest","c":"Habersham","z":["30535","30544"],"lat":34.6316,"lng":-83.5697},{"n":"Denton","c":"Jeff Davis","z":["31532"],"lat":31.796,"lng":-82.7071},{"n":"Dewy Rose","c":"Elbert","z":["30634"],"lat":34.1853,"lng":-82.9434},{"n":"Dexter","c":"Laurens","z":["31019"],"lat":32.4284,"lng":-83.0445},{"n":"Dillard","c":"Rabun","z":["30537"],"lat":34.97,"lng":-83.3575},{"n":"Dixie","c":"Brooks","z":["31629"],"lat":30.7613,"lng":-83.7082},{"n":"Doerun","c":"Colquitt","z":["31744"],"lat":31.272,"lng":-83.89},{"n":"Donalsonville","c":"Seminole","z":["31745"],"lat":30.9182,"lng":-84.8672},{"n":"Douglas","c":"Coffee","z":["31533","31534","31535"],"lat":31.5093,"lng":-82.8571},{"n":"Douglasville","c":"Douglas","z":["30133","30134","30135","30154"],"lat":33.6897,"lng":-84.7446},{"n":"Dover","c":"Screven","z":["30424"],"lat":32.7676,"lng":-81.6291},{"n":"Dry Branch","c":"Twiggs","z":["31020"],"lat":32.7151,"lng":-83.4558},{"n":"Du Pont","c":"Clinch","z":["31630"],"lat":30.9759,"lng":-82.8807},{"n":"Dublin","c":"Laurens","z":["31021","31027","31040"],"lat":32.4593,"lng":-82.9381},{"n":"Dudley","c":"Laurens","z":["31022"],"lat":32.5057,"lng":-83.109},{"n":"Duluth","c":"Gwinnett","z":["30095","30096","30097","30098","30099"],"lat":34.0256,"lng":-84.1304},{"n":"East Ellijay","c":"Gilmer","z":["30539"],"lat":34.6585,"lng":-84.4932},{"n":"Eastanollee","c":"Stephens","z":["30538"],"lat":34.5351,"lng":-83.2587},{"n":"Eastman","c":"Dodge","z":["31023"],"lat":32.1436,"lng":-83.1944},{"n":"Eatonton","c":"Putnam","z":["31024"],"lat":33.3208,"lng":-83.3559},{"n":"Eden","c":"Effingham","z":["31307"],"lat":32.174,"lng":-81.3538},{"n":"Edison","c":"Calhoun","z":["31746"],"lat":31.5069,"lng":-84.721},{"n":"Elberton","c":"Elbert","z":["30635"],"lat":34.1297,"lng":-82.841},{"n":"Elko","c":"Houston","z":["31025"],"lat":32.3602,"lng":-83.749},{"n":"Ellabell","c":"Bryan","z":["31308"],"lat":32.1592,"lng":-81.503},{"n":"Ellaville","c":"Schley","z":["31806"],"lat":32.209,"lng":-84.2771},{"n":"Ellenton","c":"Colquitt","z":["31747"],"lat":31.1789,"lng":-83.5889},{"n":"Ellenwood","c":"Clayton","z":["30294"],"lat":33.6166,"lng":-84.2939},{"n":"Ellerslie","c":"Harris","z":["31807"],"lat":32.6312,"lng":-84.7895},{"n":"Ellijay","c":"Gilmer","z":["30540"],"lat":34.7013,"lng":-84.449},{"n":"Emerson","c":"Bartow","z":["30137"],"lat":34.1184,"lng":-84.7623},{"n":"Enigma","c":"Berrien","z":["31749"],"lat":31.4178,"lng":-83.3553},{"n":"Epworth","c":"Fannin","z":["30541"],"lat":34.9287,"lng":-84.4368},{"n":"Esom Hill","c":"Polk","z":["30138"],"lat":33.9999,"lng":-85.1723},{"n":"Eton","c":"Murray","z":["30724"],"lat":34.7878,"lng":-84.7779},{"n":"Evans","c":"Columbia","z":["30809"],"lat":33.5511,"lng":-82.1436},{"n":"Experiment","c":"Spalding","z":["30212"],"lat":33.2782,"lng":-84.2888},{"n":"Fairburn","c":"Fulton","z":["30213"],"lat":33.5915,"lng":-84.6089},{"n":"Fairmount","c":"Gordon","z":["30139"],"lat":34.4625,"lng":-84.743},{"n":"Fargo","c":"Clinch","z":["31631"],"lat":31.0568,"lng":-82.7724},{"n":"Farmington","c":"Oconee","z":["30638"],"lat":33.7558,"lng":-83.4201},{"n":"Fayetteville","c":"Fayette","z":["30214","30215"],"lat":33.4679,"lng":-84.4806},{"n":"Felton","c":"Haralson","z":["30140"],"lat":33.8823,"lng":-85.2349},{"n":"Fitzgerald","c":"Ben Hill","z":["31750"],"lat":31.7488,"lng":-83.2354},{"n":"Fleming","c":"Liberty","z":["31309"],"lat":31.8767,"lng":-81.458},{"n":"Flintstone","c":"Walker","z":["30725"],"lat":34.8468,"lng":-85.238},{"n":"Flovilla","c":"Butts","z":["30216"],"lat":33.2372,"lng":-83.8983},{"n":"Flowery Branch","c":"Hall","z":["30542"],"lat":34.2828,"lng":-83.8915},{"n":"Folkston","c":"Charlton","z":["31537"],"lat":30.8553,"lng":-82.0273},{"n":"Forest Park","c":"Clayton","z":["30297","30298"],"lat":33.6115,"lng":-84.3745},{"n":"Forsyth","c":"Monroe","z":["31029"],"lat":33.0259,"lng":-83.915},{"n":"Fort Benning","c":"Muscogee","z":["31905","31995"],"lat":32.3923,"lng":-84.9315},{"n":"Fort Gaines","c":"Clay","z":["31751"],"lat":31.6362,"lng":-85.0549},{"n":"Fort Oglethorpe","c":"Catoosa","z":["30742"],"lat":34.9315,"lng":-85.175},{"n":"Fort Stewart","c":"Liberty","z":["31314","31315"],"lat":31.8068,"lng":-81.4371},{"n":"Fort Valley","c":"Peach","z":["31030"],"lat":32.5607,"lng":-83.8545},{"n":"Fortson","c":"Muscogee","z":["31808"],"lat":32.5639,"lng":-84.9915},{"n":"Fowlstown","c":"Decatur","z":["31752"],"lat":30.7919,"lng":-84.5499},{"n":"Franklin","c":"Heard","z":["30217"],"lat":33.278,"lng":-85.134},{"n":"Franklin Springs","c":"Franklin","z":["30639"],"lat":34.2743,"lng":-83.147},{"n":"Funston","c":"Colquitt","z":["31753"],"lat":31.2054,"lng":-83.8776},{"n":"Gainesville","c":"Hall","z":["30501","30503","30504","30506","30507"],"lat":34.3344,"lng":-83.8379},{"n":"Garfield","c":"Emanuel","z":["30425"],"lat":32.6549,"lng":-82.1002},{"n":"Gay","c":"Meriwether","z":["30218"],"lat":33.0691,"lng":-84.6132},{"n":"Geneva","c":"Talbot","z":["31810"],"lat":32.7011,"lng":-84.4949},{"n":"Georgetown","c":"Quitman","z":["31754"],"lat":31.8449,"lng":-85.1044},{"n":"Gibson","c":"Glascock","z":["30810"],"lat":33.2235,"lng":-82.5997},{"n":"Gillsville","c":"Hall","z":["30543"],"lat":34.3644,"lng":-83.7354},{"n":"Girard","c":"Burke","z":["30426"],"lat":33.0539,"lng":-81.6845},{"n":"Glenn","c":"Heard","z":["30219"],"lat":33.1572,"lng":-85.1706},{"n":"Glennville","c":"Tattnall","z":["30427"],"lat":32.0666,"lng":-82.0123},{"n":"Glenwood","c":"Wheeler","z":["30428"],"lat":32.1188,"lng":-82.7246},{"n":"Good Hope","c":"Walton","z":["30641"],"lat":33.7783,"lng":-83.5804},{"n":"Gordon","c":"Wilkinson","z":["31031"],"lat":32.8813,"lng":-83.3029},{"n":"Gough","c":"Burke","z":["30811"],"lat":33.0505,"lng":-81.9292},{"n":"Gracewood","c":"Richmond","z":["30812"],"lat":33.386,"lng":-82.091},{"n":"Grantville","c":"Coweta","z":["30220"],"lat":33.2756,"lng":-84.7413},{"n":"Gray","c":"Jones","z":["31032"],"lat":32.9916,"lng":-83.5674},{"n":"Grayson","c":"Gwinnett","z":["30017"],"lat":33.9169,"lng":-84.041},{"n":"Graysville","c":"Catoosa","z":["30726"],"lat":34.9802,"lng":-85.1408},{"n":"Greensboro","c":"Greene","z":["30642"],"lat":33.5607,"lng":-83.1934},{"n":"Greenville","c":"Meriwether","z":["30222"],"lat":33.0468,"lng":-84.7402},{"n":"Griffin","c":"Spalding","z":["30223","30224"],"lat":33.2659,"lng":-84.2896},{"n":"Grovetown","c":"Columbia","z":["30813"],"lat":33.4667,"lng":-82.214},{"n":"Guyton","c":"Effingham","z":["31312"],"lat":32.3316,"lng":-81.3842},{"n":"Haddock","c":"Jones","z":["31033"],"lat":33.0565,"lng":-83.4247},{"n":"Hagan","c":"Evans","z":["30429"],"lat":32.1528,"lng":-81.9259},{"n":"Hahira","c":"Lowndes","z":["31632"],"lat":30.942,"lng":-83.3332},{"n":"Hamilton","c":"Harris","z":["31811"],"lat":32.746,"lng":-84.9349},{"n":"Hampton","c":"Henry","z":["30228"],"lat":33.4081,"lng":-84.2738},{"n":"Haralson","c":"Coweta","z":["30229"],"lat":33.2322,"lng":-84.5685},{"n":"Hardwick","c":"Baldwin","z":["31034"],"lat":33.0227,"lng":-83.247},{"n":"Harlem","c":"Columbia","z":["30814"],"lat":33.4561,"lng":-82.3073},{"n":"Harrison","c":"Washington","z":["31035"],"lat":32.8553,"lng":-82.7024},{"n":"Hartsfield","c":"Colquitt","z":["31756"],"lat":31.2008,"lng":-83.9455},{"n":"Hartwell","c":"Hart","z":["30643"],"lat":34.3612,"lng":-82.9417},{"n":"Hawkinsville","c":"Pulaski","z":["31036"],"lat":32.2757,"lng":-83.4901},{"n":"Hazlehurst","c":"Jeff Davis","z":["31539"],"lat":31.8069,"lng":-82.627},{"n":"Helen","c":"White","z":["30545"],"lat":34.7292,"lng":-83.7209},{"n":"Helena","c":"Telfair","z":["31037"],"lat":32.0475,"lng":-82.9747},{"n":"Hephzibah","c":"Richmond","z":["30815"],"lat":33.3223,"lng":-82.058},{"n":"Hiawassee","c":"Towns","z":["30546"],"lat":34.9063,"lng":-83.7274},{"n":"High Shoals","c":"Morgan","z":["30645"],"lat":33.8013,"lng":-83.5164},{"n":"Hillsboro","c":"Jasper","z":["31038"],"lat":33.2075,"lng":-83.6181},{"n":"Hinesville","c":"Liberty","z":["31310","31313"],"lat":31.8068,"lng":-81.4371},{"n":"Hiram","c":"Paulding","z":["30141"],"lat":33.8794,"lng":-84.8443},{"n":"Hoboken","c":"Brantley","z":["31542"],"lat":31.179,"lng":-82.1237},{"n":"Hogansville","c":"Troup","z":["30230"],"lat":33.1442,"lng":-84.9606},{"n":"Holly Springs","c":"Cherokee","z":["30142"],"lat":34.2429,"lng":-84.4583},{"n":"Homer","c":"Banks","z":["30547"],"lat":34.3731,"lng":-83.4919},{"n":"Homerville","c":"Clinch","z":["31634"],"lat":31.0509,"lng":-82.7613},{"n":"Hortense","c":"Brantley","z":["31543"],"lat":31.2684,"lng":-81.8104},{"n":"Hoschton","c":"Jackson","z":["30548"],"lat":34.099,"lng":-83.7182},{"n":"Howard","c":"Taylor","z":["31039"],"lat":32.5598,"lng":-84.2277},{"n":"Hull","c":"Madison","z":["30646"],"lat":34.0887,"lng":-83.3091},{"n":"Ideal","c":"Macon","z":["31041"],"lat":32.3729,"lng":-84.2122},{"n":"Ila","c":"Madison","z":["30647"],"lat":34.1202,"lng":-83.2881},{"n":"Inman","c":"Fayette","z":["30232"],"lat":33.4038,"lng":-84.5044},{"n":"Iron City","c":"Seminole","z":["31759"],"lat":30.9851,"lng":-84.8347},{"n":"Irwinton","c":"Wilkinson","z":["31042"],"lat":32.7514,"lng":-83.1452},{"n":"Irwinville","c":"Irwin","z":["31760"],"lat":31.7063,"lng":-83.4086},{"n":"Jackson","c":"Butts","z":["30233"],"lat":33.3199,"lng":-83.9811},{"n":"Jacksonville","c":"Telfair","z":["31544"],"lat":31.8325,"lng":-82.9772},{"n":"Jakin","c":"Early","z":["31761"],"lat":31.0894,"lng":-84.9861},{"n":"Jasper","c":"Pickens","z":["30143"],"lat":34.469,"lng":-84.4282},{"n":"Jefferson","c":"Jackson","z":["30549"],"lat":34.106,"lng":-83.589},{"n":"Jeffersonville","c":"Twiggs","z":["31044"],"lat":32.6613,"lng":-83.331},{"n":"Jekyll Island","c":"Glynn","z":["31527"],"lat":31.0597,"lng":-81.4167},{"n":"Jenkinsburg","c":"Butts","z":["30234"],"lat":33.3224,"lng":-84.0287},{"n":"Jersey","c":"Walton","z":["30018"],"lat":33.718,"lng":-83.8015},{"n":"Jesup","c":"Wayne","z":["31545","31546","31598","31599"],"lat":31.6008,"lng":-81.9578},{"n":"Jewell","c":"Warren","z":["31045"],"lat":33.2966,"lng":-82.7556},{"n":"Jonesboro","c":"Clayton","z":["30236","30237","30238"],"lat":33.5185,"lng":-84.3375},{"n":"Juliette","c":"Monroe","z":["31046"],"lat":33.0276,"lng":-83.8032},{"n":"Junction City","c":"Talbot","z":["31812"],"lat":32.7011,"lng":-84.4949},{"n":"Kathleen","c":"Houston","z":["31047"],"lat":32.4543,"lng":-83.6464},{"n":"Kennesaw","c":"Cobb","z":["30144","30152","30156","30160"],"lat":34.0338,"lng":-84.5974},{"n":"Keysville","c":"Burke","z":["30816"],"lat":33.1551,"lng":-82.1349},{"n":"Kings Bay","c":"Camden","z":["31547"],"lat":30.8047,"lng":-81.6277},{"n":"Kingsland","c":"Camden","z":["31548"],"lat":30.7844,"lng":-81.692},{"n":"Kingston","c":"Bartow","z":["30145"],"lat":34.2339,"lng":-84.9621},{"n":"Kite","c":"Johnson","z":["31049"],"lat":32.699,"lng":-82.5253},{"n":"Knoxville","c":"Crawford","z":["31050"],"lat":32.7156,"lng":-83.9158},{"n":"La Fayette","c":"Walker","z":["30728"],"lat":34.697,"lng":-85.2553},{"n":"Lagrange","c":"Troup","z":["30240","30241","30261"],"lat":33.0243,"lng":-85.0739},{"n":"Lake Park","c":"Lowndes","z":["31636"],"lat":30.7453,"lng":-83.1843},{"n":"Lakeland","c":"Lanier","z":["31635"],"lat":31.0353,"lng":-83.0987},{"n":"Lakemont","c":"Rabun","z":["30552"],"lat":34.7899,"lng":-83.4434},{"n":"Lavonia","c":"Franklin","z":["30553"],"lat":34.408,"lng":-83.1442},{"n":"Lawrenceville","c":"Gwinnett","z":["30042","30043","30044","30045","30046","30049"],"lat":33.9295,"lng":-84.1032},{"n":"Leary","c":"Calhoun","z":["31762"],"lat":31.4843,"lng":-84.5137},{"n":"Lebanon","c":"Cherokee","z":["30146"],"lat":34.2429,"lng":-84.4583},{"n":"Leesburg","c":"Lee","z":["31763"],"lat":31.7637,"lng":-84.1604},{"n":"Lenox","c":"Cook","z":["31637"],"lat":31.271,"lng":-83.4685},{"n":"Leslie","c":"Sumter","z":["31764"],"lat":32.0001,"lng":-84.0884},{"n":"Lexington","c":"Oglethorpe","z":["30648"],"lat":33.8528,"lng":-83.0203},{"n":"Lilburn","c":"Gwinnett","z":["30047","30048"],"lat":33.8656,"lng":-84.0725},{"n":"Lilly","c":"Dooly","z":["31051"],"lat":32.1469,"lng":-83.8913},{"n":"Lincolnton","c":"Lincoln","z":["30817"],"lat":33.8127,"lng":-82.4535},{"n":"Lindale","c":"Floyd","z":["30147"],"lat":34.1522,"lng":-85.2204},{"n":"Lithia Springs","c":"Douglas","z":["30122"],"lat":33.7655,"lng":-84.6469},{"n":"Lithonia","c":"Dekalb","z":["30038","30058"],"lat":33.6675,"lng":-84.1448},{"n":"Lizella","c":"Crawford","z":["31052"],"lat":32.7833,"lng":-83.823},{"n":"Locust Grove","c":"Henry","z":["30248"],"lat":33.3721,"lng":-84.1156},{"n":"Loganville","c":"Gwinnett","z":["30052"],"lat":33.8769,"lng":-83.8968},{"n":"Lookout Mountain","c":"Walker","z":["30750"],"lat":34.9347,"lng":-85.3846},{"n":"Louisville","c":"Jefferson","z":["30434"],"lat":33.0288,"lng":-82.438},{"n":"Louvale","c":"Stewart","z":["31814"],"lat":32.0766,"lng":-84.8497},{"n":"Lovejoy","c":"Clayton","z":["30250"],"lat":33.4429,"lng":-84.3136},{"n":"Ludowici","c":"Long","z":["31316"],"lat":31.781,"lng":-81.7739},{"n":"Lula","c":"Hall","z":["30554"],"lat":34.4109,"lng":-83.7039},{"n":"Lumber City","c":"Telfair","z":["31549"],"lat":31.9314,"lng":-82.683},{"n":"Lumpkin","c":"Stewart","z":["31815"],"lat":32.0695,"lng":-84.7281},{"n":"Luthersville","c":"Meriwether","z":["30251"],"lat":33.1792,"lng":-84.6995},{"n":"Lyerly","c":"Chattooga","z":["30730"],"lat":34.3921,"lng":-85.4174},{"n":"Lyons","c":"Toombs","z":["30436"],"lat":32.1291,"lng":-82.3305},{"n":"Mableton","c":"Cobb","z":["30126"],"lat":33.8332,"lng":-84.6031},{"n":"Macon","c":"Bibb","z":["31201","31202","31203","31204","31205","31206","31207","31208","31209","31210","31211","31212","31213","31216","31217","31220","31221","31294","31295","31296","31297","31298","31299"],"lat":32.8279,"lng":-83.5951},{"n":"Madison","c":"Morgan","z":["30650"],"lat":33.5911,"lng":-83.4929},{"n":"Manassas","c":"Tattnall","z":["30438"],"lat":32.0507,"lng":-81.9983},{"n":"Manchester","c":"Meriwether","z":["31816"],"lat":32.9111,"lng":-84.6155},{"n":"Manor","c":"Ware","z":["31550"],"lat":31.1681,"lng":-82.5948},{"n":"Mansfield","c":"Jasper","z":["30055"],"lat":33.4314,"lng":-83.7908},{"n":"Marble Hill","c":"Pickens","z":["30148"],"lat":34.4398,"lng":-84.303},{"n":"Marietta","c":"Cobb","z":["30006","30007","30008","30060","30061","30062","30063","30064","30065","30066","30067","30068","30069","30090"],"lat":33.9125,"lng":-84.5572},{"n":"Marshallville","c":"Macon","z":["31057"],"lat":32.4383,"lng":-83.905},{"n":"Martin","c":"Stephens","z":["30557"],"lat":34.528,"lng":-83.2321},{"n":"Matthews","c":"Jefferson","z":["30818"],"lat":33.19,"lng":-82.3434},{"n":"Mauk","c":"Taylor","z":["31058"],"lat":32.5598,"lng":-84.2277},{"n":"Maxeys","c":"Oglethorpe","z":["30671"],"lat":33.7405,"lng":-83.1706},{"n":"Maysville","c":"Banks","z":["30558"],"lat":34.3294,"lng":-83.5434},{"n":"Mc Caysville","c":"Fannin","z":["30555"],"lat":34.937,"lng":-84.4037},{"n":"Mc Intyre","c":"Wilkinson","z":["31054"],"lat":32.8865,"lng":-83.2317},{"n":"Mc Rae","c":"Telfair","z":["31055"],"lat":32.0479,"lng":-82.9109},{"n":"Mcdonough","c":"Henry","z":["30252","30253"],"lat":33.4768,"lng":-84.055},{"n":"Meansville","c":"Pike","z":["30256"],"lat":33.0391,"lng":-84.3776},{"n":"Meigs","c":"Thomas","z":["31765"],"lat":31.0219,"lng":-84.0614},{"n":"Meldrim","c":"Effingham","z":["31318"],"lat":32.1499,"lng":-81.3722},{"n":"Menlo","c":"Chattooga","z":["30731"],"lat":34.5186,"lng":-85.4141},{"n":"Meridian","c":"Mcintosh","z":["31319"],"lat":31.459,"lng":-81.3689},{"n":"Mershon","c":"Pierce","z":["31551"],"lat":31.4536,"lng":-82.2304},{"n":"Mesena","c":"Warren","z":["30819"],"lat":33.4324,"lng":-82.6252},{"n":"Metter","c":"Candler","z":["30439"],"lat":32.3994,"lng":-82.0482},{"n":"Midland","c":"Muscogee","z":["31820"],"lat":32.5658,"lng":-84.851},{"n":"Midville","c":"Burke","z":["30441"],"lat":32.9264,"lng":-82.1723},{"n":"Midway","c":"Liberty","z":["31320"],"lat":31.7788,"lng":-81.4206},{"n":"Milan","c":"Telfair","z":["31060"],"lat":31.964,"lng":-82.9266},{"n":"Milledgeville","c":"Baldwin","z":["31059","31061","31062"],"lat":33.0813,"lng":-83.2267},{"n":"Millen","c":"Jenkins","z":["30442"],"lat":32.7794,"lng":-81.9739},{"n":"Millwood","c":"Ware","z":["31552"],"lat":31.3073,"lng":-82.6007},{"n":"Milner","c":"Lamar","z":["30257"],"lat":33.1365,"lng":-84.1487},{"n":"Mineral Bluff","c":"Fannin","z":["30559"],"lat":34.9367,"lng":-84.2689},{"n":"Mitchell","c":"Glascock","z":["30820"],"lat":33.2316,"lng":-82.6312},{"n":"Molena","c":"Pike","z":["30258"],"lat":33.0223,"lng":-84.4369},{"n":"Monroe","c":"Walton","z":["30655","30656"],"lat":33.7883,"lng":-83.7013},{"n":"Montezuma","c":"Macon","z":["31063"],"lat":32.2404,"lng":-83.864},{"n":"Monticello","c":"Jasper","z":["31064"],"lat":33.3379,"lng":-83.6985},{"n":"Montrose","c":"Laurens","z":["31065"],"lat":32.562,"lng":-83.1597},{"n":"Moreland","c":"Coweta","z":["30259"],"lat":33.2763,"lng":-84.7387},{"n":"Morgan","c":"Calhoun","z":["31766"],"lat":31.538,"lng":-84.6116},{"n":"Morganton","c":"Fannin","z":["30560"],"lat":34.8626,"lng":-84.2486},{"n":"Morris","c":"Quitman","z":["31767"],"lat":31.8814,"lng":-85.0245},{"n":"Morrow","c":"Clayton","z":["30260","30287"],"lat":33.5802,"lng":-84.3268},{"n":"Morven","c":"Brooks","z":["31638"],"lat":30.9248,"lng":-83.54},{"n":"Moultrie","c":"Colquitt","z":["31768","31776"],"lat":31.1834,"lng":-83.7897},{"n":"Mount Airy","c":"Habersham","z":["30563"],"lat":34.5417,"lng":-83.5228},{"n":"Mount Berry","c":"Floyd","z":["30149"],"lat":34.2804,"lng":-85.1821},{"n":"Mount Vernon","c":"Montgomery","z":["30445"],"lat":32.1832,"lng":-82.5667},{"n":"Mount Zion","c":"Carroll","z":["30150"],"lat":33.643,"lng":-85.1818},{"n":"Mountain City","c":"Rabun","z":["30562"],"lat":34.9144,"lng":-83.4028},{"n":"Murrayville","c":"Hall","z":["30564"],"lat":34.4454,"lng":-83.9065},{"n":"Musella","c":"Crawford","z":["31066"],"lat":32.7868,"lng":-83.9792},{"n":"Mystic","c":"Irwin","z":["31769"],"lat":31.6209,"lng":-83.2498},{"n":"Nahunta","c":"Brantley","z":["31553"],"lat":31.1583,"lng":-81.9545},{"n":"Nashville","c":"Berrien","z":["31639"],"lat":31.1998,"lng":-83.2182},{"n":"Naylor","c":"Lowndes","z":["31641"],"lat":30.899,"lng":-83.1285},{"n":"Nelson","c":"Cherokee","z":["30151"],"lat":34.2429,"lng":-84.4583},{"n":"Newborn","c":"Newton","z":["30056"],"lat":33.5149,"lng":-83.7072},{"n":"Newington","c":"Screven","z":["30446"],"lat":32.581,"lng":-81.4826},{"n":"Newnan","c":"Coweta","z":["30263","30264","30265","30271"],"lat":33.3696,"lng":-84.8194},{"n":"Newton","c":"Baker","z":["31770"],"lat":31.3717,"lng":-84.3383},{"n":"Nicholls","c":"Coffee","z":["31554"],"lat":31.5049,"lng":-82.7031},{"n":"Nicholson","c":"Jackson","z":["30565"],"lat":34.1134,"lng":-83.4746},{"n":"Norcross","c":"Gwinnett","z":["30003","30010","30071","30091","30092","30093"],"lat":33.9604,"lng":-84.0379},{"n":"Norman Park","c":"Colquitt","z":["31771"],"lat":31.2462,"lng":-83.6549},{"n":"Norristown","c":"Emanuel","z":["30447"],"lat":32.5041,"lng":-82.4848},{"n":"North Metro","c":"Gwinnett","z":["30026","30029"],"lat":33.963,"lng":-84.0923},{"n":"Norwood","c":"Warren","z":["30821"],"lat":33.485,"lng":-82.7188},{"n":"Nunez","c":"Emanuel","z":["30448"],"lat":32.4759,"lng":-82.3726},{"n":"Oakfield","c":"Worth","z":["31772"],"lat":31.7266,"lng":-83.9597},{"n":"Oakman","c":"Gordon","z":["30732"],"lat":34.569,"lng":-84.7119},{"n":"Oakwood","c":"Hall","z":["30566"],"lat":34.2394,"lng":-83.8976},{"n":"Ochlocknee","c":"Thomas","z":["31773"],"lat":30.9686,"lng":-84.0272},{"n":"Ocilla","c":"Irwin","z":["31774"],"lat":31.5718,"lng":-83.2696},{"n":"Oconee","c":"Washington","z":["31067"],"lat":32.8767,"lng":-82.9469},{"n":"Odum","c":"Wayne","z":["31555"],"lat":31.6851,"lng":-82.0376},{"n":"Offerman","c":"Pierce","z":["31556"],"lat":31.4126,"lng":-82.1155},{"n":"Oglethorpe","c":"Macon","z":["31068"],"lat":32.3275,"lng":-84.1015},{"n":"Oliver","c":"Screven","z":["30449"],"lat":32.5281,"lng":-81.5332},{"n":"Omaha","c":"Stewart","z":["31821"],"lat":32.0766,"lng":-84.8497},{"n":"Omega","c":"Tift","z":["31775"],"lat":31.3592,"lng":-83.5903},{"n":"Orchard Hill","c":"Spalding","z":["30266"],"lat":33.2657,"lng":-84.299},{"n":"Oxford","c":"Newton","z":["30054"],"lat":33.6706,"lng":-83.874},{"n":"Palmetto","c":"Fulton","z":["30268"],"lat":33.5592,"lng":-84.7101},{"n":"Parrott","c":"Terrell","z":["31777"],"lat":31.9117,"lng":-84.5061},{"n":"Patterson","c":"Pierce","z":["31557"],"lat":31.3697,"lng":-82.1154},{"n":"Pavo","c":"Thomas","z":["31778"],"lat":30.8692,"lng":-83.9008},{"n":"Peachtree City","c":"Fayette","z":["30269"],"lat":33.3958,"lng":-84.5682},{"n":"Pearson","c":"Atkinson","z":["31642"],"lat":31.3408,"lng":-82.8534},{"n":"Pelham","c":"Mitchell","z":["31779"],"lat":31.2256,"lng":-84.2234},{"n":"Pembroke","c":"Bryan","z":["31321"],"lat":32.01,"lng":-81.5148},{"n":"Pendergrass","c":"Jackson","z":["30567"],"lat":34.1594,"lng":-83.5971},{"n":"Perkins","c":"Jenkins","z":["30822"],"lat":32.8735,"lng":-81.8755},{"n":"Perry","c":"Houston","z":["31069"],"lat":32.4319,"lng":-83.7226},{"n":"Pine Lake","c":"Dekalb","z":["30072"],"lat":33.7906,"lng":-84.2053},{"n":"Pine Mountain","c":"Harris","z":["31822"],"lat":32.8342,"lng":-84.9046},{"n":"Pine Mountain Valley","c":"Harris","z":["31823"],"lat":32.8226,"lng":-84.8204},{"n":"Pinehurst","c":"Dooly","z":["31070"],"lat":32.1827,"lng":-83.7784},{"n":"Pineview","c":"Wilcox","z":["31071"],"lat":32.0981,"lng":-83.5045},{"n":"Pitts","c":"Wilcox","z":["31072"],"lat":31.9486,"lng":-83.5395},{"n":"Plainfield","c":"Dodge","z":["31073"],"lat":32.1764,"lng":-83.1229},{"n":"Plains","c":"Sumter","z":["31780"],"lat":32.0277,"lng":-84.3725},{"n":"Plainville","c":"Gordon","z":["30733"],"lat":34.414,"lng":-85.0526},{"n":"Pooler","c":"Chatham","z":["31322"],"lat":32.0719,"lng":-81.0839},{"n":"Portal","c":"Bulloch","z":["30450"],"lat":32.5521,"lng":-81.9242},{"n":"Porterdale","c":"Newton","z":["30070"],"lat":33.5712,"lng":-83.8951},{"n":"Poulan","c":"Worth","z":["31781"],"lat":31.5384,"lng":-83.7843},{"n":"Powder Springs","c":"Cobb","z":["30127"],"lat":33.9135,"lng":-84.6859},{"n":"Preston","c":"Webster","z":["31824"],"lat":32.0761,"lng":-84.5435},{"n":"Pulaski","c":"Candler","z":["30451"],"lat":32.4143,"lng":-82.0867},{"n":"Putney","c":"Dougherty","z":["31782"],"lat":31.5431,"lng":-84.2196},{"n":"Quitman","c":"Brooks","z":["31643"],"lat":30.7894,"lng":-83.5878},{"n":"Rabun Gap","c":"Rabun","z":["30568"],"lat":34.9446,"lng":-83.3814},{"n":"Ranger","c":"Gordon","z":["30734"],"lat":34.5351,"lng":-84.7242},{"n":"Ray City","c":"Berrien","z":["31645"],"lat":31.0836,"lng":-83.2287},{"n":"Rayle","c":"Wilkes","z":["30660"],"lat":33.7638,"lng":-82.8998},{"n":"Rebecca","c":"Turner","z":["31783"],"lat":31.7804,"lng":-83.526},{"n":"Red Oak","c":"Fulton","z":["30272"],"lat":33.6259,"lng":-84.5163},{"n":"Redan","c":"Dekalb","z":["30074"],"lat":33.8913,"lng":-84.0746},{"n":"Register","c":"Bulloch","z":["30452"],"lat":32.398,"lng":-81.8892},{"n":"Reidsville","c":"Tattnall","z":["30453","30499"],"lat":32.0311,"lng":-82.146},{"n":"Rentz","c":"Laurens","z":["31075"],"lat":32.3799,"lng":-82.967},{"n":"Resaca","c":"Gordon","z":["30735"],"lat":34.5833,"lng":-84.9068},{"n":"Rex","c":"Clayton","z":["30273"],"lat":33.577,"lng":-84.2726},{"n":"Reynolds","c":"Taylor","z":["31076"],"lat":32.5517,"lng":-84.0927},{"n":"Rhine","c":"Dodge","z":["31077"],"lat":32.1764,"lng":-83.1229},{"n":"Riceboro","c":"Liberty","z":["31323"],"lat":31.7859,"lng":-81.5738},{"n":"Richland","c":"Stewart","z":["31825"],"lat":32.0743,"lng":-84.7186},{"n":"Richmond Hill","c":"Bryan","z":["31324"],"lat":31.9515,"lng":-81.4073},{"n":"Rincon","c":"Effingham","z":["31326"],"lat":32.2852,"lng":-81.2875},{"n":"Ringgold","c":"Catoosa","z":["30736"],"lat":34.8887,"lng":-85.1187},{"n":"Rising Fawn","c":"Dade","z":["30738"],"lat":34.8139,"lng":-85.5019},{"n":"Riverdale","c":"Clayton","z":["30274","30296"],"lat":33.5555,"lng":-84.398},{"n":"Roberta","c":"Crawford","z":["31078"],"lat":32.6872,"lng":-84.0106},{"n":"Rochelle","c":"Wilcox","z":["31079"],"lat":31.9484,"lng":-83.4536},{"n":"Rock Spring","c":"Walker","z":["30739"],"lat":34.8018,"lng":-85.2128},{"n":"Rockledge","c":"Laurens","z":["30454"],"lat":32.5063,"lng":-82.7137},{"n":"Rockmart","c":"Polk","z":["30153"],"lat":33.9938,"lng":-85.0915},{"n":"Rocky Face","c":"Whitfield","z":["30740"],"lat":34.767,"lng":-85.0727},{"n":"Rocky Ford","c":"Screven","z":["30455"],"lat":32.723,"lng":-81.7933},{"n":"Rome","c":"Floyd","z":["30161","30162","30163","30164","30165"],"lat":34.2623,"lng":-85.2209},{"n":"Roopville","c":"Carroll","z":["30170"],"lat":33.5242,"lng":-85.1653},{"n":"Rossville","c":"Walker","z":["30741"],"lat":34.7981,"lng":-85.2463},{"n":"Roswell","c":"Fulton","z":["30075","30076","30077"],"lat":34.0552,"lng":-84.3705},{"n":"Royston","c":"Franklin","z":["30662"],"lat":34.298,"lng":-83.1928},{"n":"Rupert","c":"Taylor","z":["31081"],"lat":32.5598,"lng":-84.2277},{"n":"Rutledge","c":"Morgan","z":["30663"],"lat":33.611,"lng":-83.6025},{"n":"Rydal","c":"Bartow","z":["30171"],"lat":34.3379,"lng":-84.7376},{"n":"Saint George","c":"Charlton","z":["31646"],"lat":30.4343,"lng":-82.1655},{"n":"Saint Marys","c":"Camden","z":["31558"],"lat":30.844,"lng":-81.631},{"n":"Saint Simons Island","c":"Glynn","z":["31522"],"lat":31.2132,"lng":-81.4491},{"n":"Sale City","c":"Mitchell","z":["31784"],"lat":31.2743,"lng":-84.0477},{"n":"Sandersville","c":"Washington","z":["31082"],"lat":32.975,"lng":-82.8406},{"n":"Sapelo Island","c":"Mcintosh","z":["31327"],"lat":31.4951,"lng":-81.3819},{"n":"Sardis","c":"Burke","z":["30456"],"lat":32.9803,"lng":-81.8449},{"n":"Sargent","c":"Coweta","z":["30275"],"lat":33.4299,"lng":-84.8744},{"n":"Sasser","c":"Terrell","z":["31785"],"lat":31.69,"lng":-84.3275},{"n":"Sautee Nacoochee","c":"White","z":["30571"],"lat":34.6658,"lng":-83.7096},{"n":"Savannah","c":"Chatham","z":["31401","31402","31403","31404","31405","31406","31407","31408","31409","31410","31411","31412","31414","31415","31416","31418","31419","31420","31421","31422","31498","31499"],"lat":32.0723,"lng":-81.1356},{"n":"Scotland","c":"Telfair","z":["31083"],"lat":32.0841,"lng":-82.9123},{"n":"Scottdale","c":"Dekalb","z":["30079"],"lat":33.7935,"lng":-84.2584},{"n":"Screven","c":"Wayne","z":["31560"],"lat":31.5129,"lng":-82.0103},{"n":"Sea Island","c":"Glynn","z":["31561"],"lat":31.1989,"lng":-81.3322},{"n":"Senoia","c":"Coweta","z":["30276"],"lat":33.2854,"lng":-84.6025},{"n":"Seville","c":"Wilcox","z":["31084"],"lat":31.989,"lng":-83.3946},{"n":"Shady Dale","c":"Jasper","z":["31085"],"lat":33.435,"lng":-83.6269},{"n":"Shannon","c":"Floyd","z":["30172"],"lat":34.3333,"lng":-85.2337},{"n":"Sharon","c":"Taliaferro","z":["30664"],"lat":33.56,"lng":-82.7948},{"n":"Sharpsburg","c":"Coweta","z":["30277"],"lat":33.3631,"lng":-84.6594},{"n":"Shellman","c":"Randolph","z":["31786"],"lat":31.7604,"lng":-84.6149},{"n":"Shiloh","c":"Harris","z":["31826"],"lat":32.7913,"lng":-84.7336},{"n":"Siloam","c":"Greene","z":["30665"],"lat":33.5619,"lng":-83.0742},{"n":"Silver Creek","c":"Floyd","z":["30173"],"lat":34.1455,"lng":-85.1177},{"n":"Smarr","c":"Monroe","z":["31086"],"lat":32.9895,"lng":-83.8761},{"n":"Smithville","c":"Lee","z":["31787"],"lat":31.7721,"lng":-84.2225},{"n":"Smyrna","c":"Cobb","z":["30080","30081","30082"],"lat":33.8646,"lng":-84.5562},{"n":"Snellville","c":"Gwinnett","z":["30039","30078"],"lat":33.8178,"lng":-84.0229},{"n":"Social Circle","c":"Walton","z":["30025"],"lat":33.6791,"lng":-83.6835},{"n":"Soperton","c":"Treutlen","z":["30457"],"lat":32.3831,"lng":-82.5571},{"n":"Sparks","c":"Cook","z":["31647"],"lat":31.2129,"lng":-83.4121},{"n":"Sparta","c":"Hancock","z":["31087"],"lat":33.2571,"lng":-83.0892},{"n":"Springfield","c":"Effingham","z":["31329"],"lat":32.3697,"lng":-81.3618},{"n":"Stapleton","c":"Jefferson","z":["30823"],"lat":33.1814,"lng":-82.4386},{"n":"Statenville","c":"Echols","z":["31648"],"lat":30.7689,"lng":-83.0371},{"n":"Statesboro","c":"Bulloch","z":["30458","30459","30460","30461"],"lat":32.425,"lng":-81.785},{"n":"Statham","c":"Barrow","z":["30666"],"lat":33.9803,"lng":-83.5901},{"n":"Stephens","c":"Oglethorpe","z":["30667"],"lat":33.8046,"lng":-83.1517},{"n":"Stillmore","c":"Emanuel","z":["30464"],"lat":32.4459,"lng":-82.2587},{"n":"Stockbridge","c":"Henry","z":["30281"],"lat":33.5499,"lng":-84.208},{"n":"Stockton","c":"Lanier","z":["31649"],"lat":30.9551,"lng":-83.0138},{"n":"Stone Mountain","c":"Dekalb","z":["30083","30086","30087","30088"],"lat":33.7864,"lng":-84.2034},{"n":"Suches","c":"Union","z":["30572"],"lat":34.7121,"lng":-84.0276},{"n":"Sugar Valley","c":"Gordon","z":["30746"],"lat":34.5718,"lng":-85.0256},{"n":"Summerville","c":"Chattooga","z":["30747"],"lat":34.4842,"lng":-85.3155},{"n":"Sumner","c":"Worth","z":["31789"],"lat":31.4818,"lng":-83.7273},{"n":"Sunny Side","c":"Spalding","z":["30284"],"lat":33.3453,"lng":-84.2898},{"n":"Surrency","c":"Appling","z":["31563"],"lat":31.7312,"lng":-82.1949},{"n":"Suwanee","c":"Gwinnett","z":["30024"],"lat":34.0425,"lng":-84.0262},{"n":"Swainsboro","c":"Emanuel","z":["30401"],"lat":32.5699,"lng":-82.3462},{"n":"Sycamore","c":"Turner","z":["31790"],"lat":31.6529,"lng":-83.5783},{"n":"Sylvania","c":"Screven","z":["30467"],"lat":32.7439,"lng":-81.6287},{"n":"Sylvester","c":"Worth","z":["31791"],"lat":31.6033,"lng":-83.8501},{"n":"Talbotton","c":"Talbot","z":["31827"],"lat":32.6737,"lng":-84.538},{"n":"Talking Rock","c":"Pickens","z":["30175"],"lat":34.5157,"lng":-84.5234},{"n":"Tallapoosa","c":"Haralson","z":["30176"],"lat":33.7701,"lng":-85.2616},{"n":"Tallulah Falls","c":"Rabun","z":["30573"],"lat":34.742,"lng":-83.3977},{"n":"Talmo","c":"Jackson","z":["30575"],"lat":34.1951,"lng":-83.7132},{"n":"Tarrytown","c":"Montgomery","z":["30470"],"lat":32.1888,"lng":-82.5221},{"n":"Tate","c":"Pickens","z":["30177"],"lat":34.4027,"lng":-84.3785},{"n":"Taylorsville","c":"Bartow","z":["30178"],"lat":34.1296,"lng":-84.9734},{"n":"Temple","c":"Carroll","z":["30179"],"lat":33.7375,"lng":-85.0261},{"n":"Tennga","c":"Murray","z":["30751"],"lat":34.9814,"lng":-84.7352},{"n":"Tennille","c":"Washington","z":["31089"],"lat":32.8734,"lng":-82.7829},{"n":"The Rock","c":"Upson","z":["30285"],"lat":32.965,"lng":-84.2193},{"n":"Thomaston","c":"Upson","z":["30286"],"lat":32.8845,"lng":-84.3365},{"n":"Thomasville","c":"Thomas","z":["31757","31758","31792","31799"],"lat":30.8536,"lng":-83.8883},{"n":"Thomson","c":"Mcduffie","z":["30824"],"lat":33.4949,"lng":-82.5138},{"n":"Tifton","c":"Tift","z":["31793","31794"],"lat":31.4854,"lng":-83.5036},{"n":"Tiger","c":"Rabun","z":["30576"],"lat":34.8564,"lng":-83.4573},{"n":"Tignall","c":"Wilkes","z":["30668"],"lat":33.8778,"lng":-82.747},{"n":"Toccoa","c":"Stephens","z":["30577"],"lat":34.5541,"lng":-83.2888},{"n":"Toccoa Falls","c":"Stephens","z":["30598"],"lat":34.5918,"lng":-83.3525},{"n":"Toomsboro","c":"Wilkinson","z":["31090"],"lat":32.8066,"lng":-83.0668},{"n":"Townsend","c":"Mcintosh","z":["31331"],"lat":31.512,"lng":-81.3583},{"n":"Trenton","c":"Dade","z":["30752"],"lat":34.8717,"lng":-85.5021},{"n":"Trion","c":"Chattooga","z":["30753"],"lat":34.5327,"lng":-85.3684},{"n":"Tucker","c":"Dekalb","z":["30084","30085"],"lat":33.8539,"lng":-84.2154},{"n":"Tunnel Hill","c":"Whitfield","z":["30755"],"lat":34.8754,"lng":-85.05},{"n":"Turin","c":"Coweta","z":["30289"],"lat":33.326,"lng":-84.6371},{"n":"Turnerville","c":"Habersham","z":["30580"],"lat":34.6766,"lng":-83.4358},{"n":"Twin City","c":"Emanuel","z":["30471"],"lat":32.5498,"lng":-82.1839},{"n":"Ty Ty","c":"Tift","z":["31795"],"lat":31.4752,"lng":-83.5921},{"n":"Tybee Island","c":"Chatham","z":["31328"],"lat":32.0059,"lng":-80.8553},{"n":"Tyrone","c":"Fayette","z":["30290"],"lat":33.46,"lng":-84.5858},{"n":"Unadilla","c":"Dooly","z":["31091"],"lat":32.2192,"lng":-83.7317},{"n":"Union City","c":"Fulton","z":["30291"],"lat":33.5731,"lng":-84.551},{"n":"Union Point","c":"Greene","z":["30669"],"lat":33.6343,"lng":-83.1221},{"n":"Upatoi","c":"Muscogee","z":["31829"],"lat":32.5648,"lng":-84.7339},{"n":"Uvalda","c":"Montgomery","z":["30473"],"lat":32.0288,"lng":-82.5162},{"n":"Valdosta","c":"Lowndes","z":["31601","31602","31603","31604","31605","31606","31698","31699"],"lat":30.7539,"lng":-83.3321},{"n":"Varnell","c":"Whitfield","z":["30756"],"lat":34.9298,"lng":-84.9885},{"n":"Vidalia","c":"Toombs","z":["30474","30475"],"lat":32.1987,"lng":-82.3921},{"n":"Vienna","c":"Dooly","z":["31092"],"lat":32.116,"lng":-83.7916},{"n":"Villa Rica","c":"Carroll","z":["30180"],"lat":33.7055,"lng":-84.9757},{"n":"Waco","c":"Haralson","z":["30182"],"lat":33.6801,"lng":-85.2513},{"n":"Wadley","c":"Jefferson","z":["30477"],"lat":32.8637,"lng":-82.4075},{"n":"Waleska","c":"Cherokee","z":["30183"],"lat":34.3386,"lng":-84.5776},{"n":"Walthourville","c":"Liberty","z":["31333"],"lat":31.7705,"lng":-81.6208},{"n":"Waresboro","c":"Ware","z":["31564"],"lat":31.019,"lng":-82.4165},{"n":"Warm Springs","c":"Meriwether","z":["31830"],"lat":32.9063,"lng":-84.7167},{"n":"Warner Robins","c":"Houston","z":["31088","31093","31095","31098","31099"],"lat":32.555,"lng":-83.6448},{"n":"Warrenton","c":"Warren","z":["30828"],"lat":33.4061,"lng":-82.6411},{"n":"Warthen","c":"Washington","z":["31094"],"lat":33.0797,"lng":-82.8056},{"n":"Warwick","c":"Worth","z":["31796"],"lat":31.7622,"lng":-83.8762},{"n":"Washington","c":"Wilkes","z":["30673"],"lat":33.7315,"lng":-82.7108},{"n":"Watkinsville","c":"Oconee","z":["30677"],"lat":33.8167,"lng":-83.4335},{"n":"Waverly","c":"Camden","z":["31565"],"lat":31.0694,"lng":-81.6337},{"n":"Waverly Hall","c":"Harris","z":["31831"],"lat":32.7387,"lng":-84.7855},{"n":"Waycross","c":"Ware","z":["31501","31502","31503"],"lat":31.2243,"lng":-82.3596},{"n":"Waynesboro","c":"Burke","z":["30830"],"lat":33.0807,"lng":-81.9868},{"n":"Waynesville","c":"Brantley","z":["31566"],"lat":31.1879,"lng":-81.8896},{"n":"West Green","c":"Coffee","z":["31567"],"lat":31.6143,"lng":-82.7243},{"n":"West Point","c":"Troup","z":["31833"],"lat":32.9073,"lng":-85.0775},{"n":"Weston","c":"Webster","z":["31832"],"lat":32.0761,"lng":-84.5435},{"n":"Whigham","c":"Grady","z":["31797"],"lat":30.902,"lng":-84.3115},{"n":"White","c":"Bartow","z":["30184"],"lat":34.2643,"lng":-84.7539},{"n":"White Oak","c":"Camden","z":["31568"],"lat":30.9952,"lng":-81.7782},{"n":"White Plains","c":"Greene","z":["30678"],"lat":33.4581,"lng":-83.0802},{"n":"Whitesburg","c":"Carroll","z":["30185"],"lat":33.509,"lng":-84.9102},{"n":"Wildwood","c":"Dade","z":["30757"],"lat":34.923,"lng":-85.4483},{"n":"Wiley","c":"Rabun","z":["30581"],"lat":34.8045,"lng":-83.4191},{"n":"Willacoochee","c":"Atkinson","z":["31650"],"lat":31.3617,"lng":-82.9682},{"n":"Williamson","c":"Pike","z":["30292"],"lat":33.117,"lng":-84.3991},{"n":"Winder","c":"Barrow","z":["30680"],"lat":33.9871,"lng":-83.6985},{"n":"Winston","c":"Douglas","z":["30187"],"lat":33.6595,"lng":-84.7782},{"n":"Winterville","c":"Clarke","z":["30683"],"lat":33.9307,"lng":-83.2922},{"n":"Woodbine","c":"Camden","z":["31569"],"lat":30.9391,"lng":-81.7035},{"n":"Woodbury","c":"Meriwether","z":["30293"],"lat":32.9682,"lng":-84.6254},{"n":"Woodland","c":"Talbot","z":["31836"],"lat":32.79,"lng":-84.5654},{"n":"Woodstock","c":"Cherokee","z":["30188","30189"],"lat":34.1274,"lng":-84.4818},{"n":"Wray","c":"Irwin","z":["31798"],"lat":31.5718,"lng":-83.0878},{"n":"Wrens","c":"Jefferson","z":["30833"],"lat":33.1924,"lng":-82.3615},{"n":"Wrightsville","c":"Johnson","z":["31096"],"lat":32.6357,"lng":-82.6575},{"n":"Yatesville","c":"Upson","z":["31097"],"lat":32.9016,"lng":-84.2126},{"n":"Young Harris","c":"Towns","z":["30582"],"lat":34.9344,"lng":-83.8285},{"n":"Zebulon","c":"Pike","z":["30295"],"lat":33.0774,"lng":-84.3217}]}