{"counties":["Belknap","Carroll","Cheshire","Coos","Grafton","Hillsborough","Merrimack","Rockingham","Strafford","Sullivan"],"cities":[{"n":"Acworth","c":"Sullivan","z":["03601"],"lat":43.196,"lng":-72.3001},{"n":"Alstead","c":"Cheshire","z":["03602"],"lat":43.1344,"lng":-72.3106},{"n":"Alton","c":"Belknap","z":["03809"],"lat":43.4626,"lng":-71.2225},{"n":"Alton Bay","c":"Belknap","z":["03810"],"lat":43.5025,"lng":-71.2774},{"n":"Amherst","c":"Hillsborough","z":["03031"],"lat":42.8747,"lng":-71.6294},{"n":"Andover","c":"Merrimack","z":["03216"],"lat":43.447,"lng":-71.6841},{"n":"Antrim","c":"Hillsborough","z":["03440"],"lat":43.0445,"lng":-71.9714},{"n":"Ashland","c":"Grafton","z":["03217"],"lat":43.7156,"lng":-71.6399},{"n":"Ashuelot","c":"Cheshire","z":["03441"],"lat":42.7773,"lng":-72.4441},{"n":"Atkinson","c":"Rockingham","z":["03811"],"lat":42.8784,"lng":-71.159},{"n":"Auburn","c":"Rockingham","z":["03032"],"lat":42.9892,"lng":-71.3436},{"n":"Barnstead","c":"Belknap","z":["03218"],"lat":43.4174,"lng":-71.3732},{"n":"Barrington","c":"Strafford","z":["03825"],"lat":43.2978,"lng":-71.0974},{"n":"Bartlett","c":"Carroll","z":["03812"],"lat":43.8839,"lng":-71.2577},{"n":"Bath","c":"Grafton","z":["03740"],"lat":44.1142,"lng":-71.9489},{"n":"Bedford","c":"Hillsborough","z":["03110"],"lat":42.9374,"lng":-71.5355},{"n":"Belmont","c":"Belknap","z":["03220"],"lat":43.4556,"lng":-71.4071},{"n":"Bennington","c":"Hillsborough","z":["03442"],"lat":43.0029,"lng":-71.908},{"n":"Berlin","c":"Coos","z":["03570"],"lat":44.5123,"lng":-71.1942},{"n":"Bethlehem","c":"Grafton","z":["03574"],"lat":44.3063,"lng":-71.728},{"n":"Bow","c":"Merrimack","z":["03304"],"lat":43.1283,"lng":-71.5446},{"n":"Bradford","c":"Merrimack","z":["03221"],"lat":43.281,"lng":-71.7925},{"n":"Bretton Woods","c":"Coos","z":["03575"],"lat":44.6956,"lng":-71.3874},{"n":"Bristol","c":"Grafton","z":["03222"],"lat":43.7078,"lng":-71.7216},{"n":"Brookline","c":"Hillsborough","z":["03033"],"lat":42.8473,"lng":-71.7674},{"n":"Campton","c":"Grafton","z":["03223"],"lat":43.8418,"lng":-71.6652},{"n":"Canaan","c":"Grafton","z":["03741"],"lat":43.6312,"lng":-72.0573},{"n":"Candia","c":"Rockingham","z":["03034"],"lat":43.0593,"lng":-71.3054},{"n":"Canterbury","c":"Merrimack","z":["03224"],"lat":43.3783,"lng":-71.6042},{"n":"Center Barnstead","c":"Belknap","z":["03225"],"lat":43.3867,"lng":-71.293},{"n":"Center Conway","c":"Carroll","z":["03813"],"lat":43.7974,"lng":-71.1454},{"n":"Center Harbor","c":"Belknap","z":["03226"],"lat":43.6939,"lng":-71.4662},{"n":"Center Ossipee","c":"Carroll","z":["03814"],"lat":43.7624,"lng":-71.1227},{"n":"Center Sandwich","c":"Carroll","z":["03227"],"lat":43.6948,"lng":-71.324},{"n":"Center Strafford","c":"Strafford","z":["03815"],"lat":43.2537,"lng":-71.1098},{"n":"Center Tuftonboro","c":"Carroll","z":["03816"],"lat":43.6608,"lng":-71.2745},{"n":"Charlestown","c":"Sullivan","z":["03603"],"lat":43.2681,"lng":-72.3702},{"n":"Chester","c":"Rockingham","z":["03036"],"lat":42.9616,"lng":-71.251},{"n":"Chesterfield","c":"Cheshire","z":["03443"],"lat":42.8839,"lng":-72.4548},{"n":"Chichester","c":"Merrimack","z":["03258"],"lat":43.2653,"lng":-71.4088},{"n":"Chocorua","c":"Carroll","z":["03817"],"lat":43.7486,"lng":-71.0898},{"n":"Claremont","c":"Sullivan","z":["03743"],"lat":43.416,"lng":-72.2098},{"n":"Colebrook","c":"Coos","z":["03576"],"lat":44.9027,"lng":-71.5008},{"n":"Concord","c":"Merrimack","z":["03301","03302","03303","03305"],"lat":43.2303,"lng":-71.5361},{"n":"Contoocook","c":"Merrimack","z":["03229"],"lat":43.3013,"lng":-71.8129},{"n":"Conway","c":"Carroll","z":["03818"],"lat":43.7889,"lng":-71.1026},{"n":"Cornish","c":"Sullivan","z":["03745"],"lat":43.4622,"lng":-72.3371},{"n":"Cornish Flat","c":"Sullivan","z":["03746"],"lat":43.3645,"lng":-72.194},{"n":"Danbury","c":"Merrimack","z":["03230"],"lat":43.5148,"lng":-71.8821},{"n":"Danville","c":"Rockingham","z":["03819"],"lat":42.9267,"lng":-71.0823},{"n":"Deerfield","c":"Rockingham","z":["03037"],"lat":42.9875,"lng":-71.2527},{"n":"Derry","c":"Rockingham","z":["03038"],"lat":42.9508,"lng":-71.1972},{"n":"Dover","c":"Strafford","z":["03820","03821","03822"],"lat":43.2973,"lng":-70.992},{"n":"Drewsville","c":"Cheshire","z":["03604"],"lat":42.9471,"lng":-72.243},{"n":"Dublin","c":"Cheshire","z":["03444"],"lat":42.8891,"lng":-72.019},{"n":"Dunbarton","c":"Merrimack","z":["03046"],"lat":43.1012,"lng":-71.605},{"n":"Durham","c":"Strafford","z":["03824"],"lat":43.1658,"lng":-70.9628},{"n":"East Andover","c":"Merrimack","z":["03231"],"lat":43.4662,"lng":-71.7365},{"n":"East Candia","c":"Rockingham","z":["03040"],"lat":43.0059,"lng":-71.0132},{"n":"East Derry","c":"Rockingham","z":["03041"],"lat":43.0059,"lng":-71.0132},{"n":"East Hampstead","c":"Rockingham","z":["03826"],"lat":42.8936,"lng":-71.1427},{"n":"East Hebron","c":"Grafton","z":["03232"],"lat":43.9675,"lng":-71.8409},{"n":"East Kingston","c":"Rockingham","z":["03827"],"lat":42.9121,"lng":-71.0542},{"n":"East Wakefield","c":"Carroll","z":["03830"],"lat":43.6351,"lng":-71.0094},{"n":"Eaton Center","c":"Carroll","z":["03832"],"lat":43.8839,"lng":-71.2577},{"n":"Effingham","c":"Carroll","z":["03882"],"lat":43.7047,"lng":-70.9902},{"n":"Elkins","c":"Merrimack","z":["03233"],"lat":43.4227,"lng":-71.9448},{"n":"Enfield","c":"Grafton","z":["03748"],"lat":43.6309,"lng":-72.1166},{"n":"Enfield Center","c":"Grafton","z":["03749"],"lat":43.5796,"lng":-72.0854},{"n":"Epping","c":"Rockingham","z":["03042"],"lat":43.0476,"lng":-71.0844},{"n":"Epsom","c":"Merrimack","z":["03234"],"lat":43.3407,"lng":-71.6697},{"n":"Errol","c":"Coos","z":["03579"],"lat":44.6956,"lng":-71.3874},{"n":"Etna","c":"Grafton","z":["03750"],"lat":43.698,"lng":-72.2152},{"n":"Exeter","c":"Rockingham","z":["03833"],"lat":42.9513,"lng":-70.9223},{"n":"Farmington","c":"Strafford","z":["03835"],"lat":43.3062,"lng":-71.0034},{"n":"Fitzwilliam","c":"Cheshire","z":["03447"],"lat":42.8818,"lng":-72.248},{"n":"Francestown","c":"Hillsborough","z":["03043"],"lat":42.9162,"lng":-71.8165},{"n":"Franconia","c":"Grafton","z":["03580"],"lat":44.2128,"lng":-71.7372},{"n":"Franklin","c":"Merrimack","z":["03235"],"lat":43.3743,"lng":-71.68},{"n":"Freedom","c":"Carroll","z":["03836"],"lat":43.8237,"lng":-71.0932},{"n":"Fremont","c":"Rockingham","z":["03044"],"lat":42.9922,"lng":-71.127},{"n":"Georges Mills","c":"Sullivan","z":["03751"],"lat":43.4487,"lng":-72.0637},{"n":"Gilford","c":"Belknap","z":["03249"],"lat":43.5586,"lng":-71.3844},{"n":"Gilmanton","c":"Belknap","z":["03237"],"lat":43.4141,"lng":-71.3842},{"n":"Gilmanton Iron Works","c":"Belknap","z":["03837"],"lat":43.4466,"lng":-71.2995},{"n":"Gilsum","c":"Cheshire","z":["03448"],"lat":42.9368,"lng":-72.211},{"n":"Glen","c":"Carroll","z":["03838"],"lat":44.0501,"lng":-71.2654},{"n":"Glencliff","c":"Grafton","z":["03238"],"lat":43.9675,"lng":-71.8409},{"n":"Goffstown","c":"Hillsborough","z":["03045"],"lat":42.9467,"lng":-71.6876},{"n":"Gorham","c":"Coos","z":["03581"],"lat":44.4048,"lng":-71.1548},{"n":"Goshen","c":"Sullivan","z":["03752"],"lat":43.4177,"lng":-72.1967},{"n":"Grafton","c":"Grafton","z":["03240"],"lat":43.9675,"lng":-71.8409},{"n":"Grantham","c":"Sullivan","z":["03753"],"lat":43.4631,"lng":-72.2184},{"n":"Greenfield","c":"Hillsborough","z":["03047"],"lat":42.9293,"lng":-71.8591},{"n":"Greenland","c":"Rockingham","z":["03840"],"lat":43.0386,"lng":-70.8092},{"n":"Greenville","c":"Hillsborough","z":["03048"],"lat":42.8751,"lng":-71.7175},{"n":"Groveton","c":"Coos","z":["03582"],"lat":44.751,"lng":-71.4225},{"n":"Guild","c":"Sullivan","z":["03754"],"lat":43.3656,"lng":-72.1256},{"n":"Hampstead","c":"Rockingham","z":["03841"],"lat":42.8774,"lng":-71.1391},{"n":"Hampton","c":"Rockingham","z":["03842","03843"],"lat":42.9174,"lng":-70.951},{"n":"Hampton Falls","c":"Rockingham","z":["03844"],"lat":42.8919,"lng":-70.9826},{"n":"Hancock","c":"Hillsborough","z":["03449"],"lat":42.9392,"lng":-71.9838},{"n":"Hanover","c":"Grafton","z":["03755"],"lat":43.8611,"lng":-72.1203},{"n":"Harrisville","c":"Cheshire","z":["03450"],"lat":42.8845,"lng":-72.1026},{"n":"Haverhill","c":"Grafton","z":["03765"],"lat":44.0375,"lng":-72.0467},{"n":"Hebron","c":"Grafton","z":["03241"],"lat":43.7183,"lng":-71.8895},{"n":"Henniker","c":"Merrimack","z":["03242"],"lat":43.1801,"lng":-71.8196},{"n":"Hill","c":"Merrimack","z":["03243"],"lat":43.4435,"lng":-71.7626},{"n":"Hillsboro","c":"Hillsborough","z":["03244"],"lat":43.123,"lng":-71.9143},{"n":"Hinsdale","c":"Cheshire","z":["03451"],"lat":42.8942,"lng":-72.2801},{"n":"Holderness","c":"Grafton","z":["03245"],"lat":43.7378,"lng":-71.6044},{"n":"Hollis","c":"Hillsborough","z":["03049"],"lat":42.8595,"lng":-71.5813},{"n":"Hooksett","c":"Merrimack","z":["03106"],"lat":43.0651,"lng":-71.4436},{"n":"Hudson","c":"Hillsborough","z":["03051"],"lat":42.7664,"lng":-71.6189},{"n":"Intervale","c":"Carroll","z":["03845"],"lat":44.0827,"lng":-71.1343},{"n":"Jackson","c":"Carroll","z":["03846"],"lat":43.8839,"lng":-71.2577},{"n":"Jaffrey","c":"Cheshire","z":["03452"],"lat":42.822,"lng":-72.0826},{"n":"Jefferson","c":"Coos","z":["03583"],"lat":44.6956,"lng":-71.3874},{"n":"Kearsarge","c":"Carroll","z":["03847"],"lat":43.8839,"lng":-71.2577},{"n":"Keene","c":"Cheshire","z":["03431","03435"],"lat":42.9037,"lng":-72.2481},{"n":"Kingston","c":"Rockingham","z":["03848"],"lat":42.9097,"lng":-71.1029},{"n":"Laconia","c":"Belknap","z":["03246","03247"],"lat":43.5355,"lng":-71.427},{"n":"Lancaster","c":"Coos","z":["03584"],"lat":44.4766,"lng":-71.5612},{"n":"Lebanon","c":"Grafton","z":["03756","03766"],"lat":43.9675,"lng":-71.8409},{"n":"Lempster","c":"Sullivan","z":["03605"],"lat":43.2136,"lng":-72.1968},{"n":"Lincoln","c":"Grafton","z":["03251"],"lat":44.0492,"lng":-71.6535},{"n":"Lisbon","c":"Grafton","z":["03585"],"lat":44.245,"lng":-71.8889},{"n":"Litchfield","c":"Hillsborough","z":["03052"],"lat":42.8868,"lng":-71.4853},{"n":"Littleton","c":"Grafton","z":["03561"],"lat":44.3353,"lng":-71.8776},{"n":"Lochmere","c":"Belknap","z":["03252"],"lat":43.4686,"lng":-71.5371},{"n":"Londonderry","c":"Rockingham","z":["03053"],"lat":42.8712,"lng":-71.3878},{"n":"Loudon","c":"Merrimack","z":["03307"],"lat":43.3193,"lng":-71.467},{"n":"Lyme","c":"Grafton","z":["03768"],"lat":43.8017,"lng":-72.1305},{"n":"Lyme Center","c":"Grafton","z":["03769"],"lat":43.7863,"lng":-72.1205},{"n":"Lyndeborough","c":"Hillsborough","z":["03082"],"lat":42.902,"lng":-71.7739},{"n":"Madison","c":"Carroll","z":["03849"],"lat":43.9023,"lng":-71.1246},{"n":"Manchester","c":"Hillsborough","z":["03101","03102","03103","03104","03105","03107","03108","03109","03111"],"lat":42.9885,"lng":-71.4621},{"n":"Marlborough","c":"Cheshire","z":["03455"],"lat":42.8882,"lng":-72.2796},{"n":"Marlow","c":"Cheshire","z":["03456"],"lat":43.1193,"lng":-72.2026},{"n":"Meadows","c":"Coos","z":["03587"],"lat":44.6956,"lng":-71.3874},{"n":"Melvin Village","c":"Carroll","z":["03850"],"lat":43.7077,"lng":-71.3017},{"n":"Meredith","c":"Belknap","z":["03253"],"lat":43.5922,"lng":-71.5175},{"n":"Meriden","c":"Sullivan","z":["03770"],"lat":43.4217,"lng":-72.2556},{"n":"Merrimack","c":"Hillsborough","z":["03054"],"lat":42.9249,"lng":-71.6675},{"n":"Milan","c":"Coos","z":["03588"],"lat":44.5653,"lng":-71.2187},{"n":"Milford","c":"Hillsborough","z":["03055"],"lat":42.8488,"lng":-71.7439},{"n":"Milton","c":"Strafford","z":["03851"],"lat":43.4229,"lng":-71.0114},{"n":"Milton Mills","c":"Strafford","z":["03852"],"lat":43.3267,"lng":-71.0284},{"n":"Mirror Lake","c":"Carroll","z":["03853"],"lat":43.6463,"lng":-71.2821},{"n":"Monroe","c":"Grafton","z":["03771"],"lat":44.2686,"lng":-72.0153},{"n":"Mont Vernon","c":"Hillsborough","z":["03057"],"lat":42.8505,"lng":-71.727},{"n":"Moultonborough","c":"Carroll","z":["03254"],"lat":43.7282,"lng":-71.3352},{"n":"Mount Washington","c":"Coos","z":["03589"],"lat":44.6956,"lng":-71.3874},{"n":"Nashua","c":"Hillsborough","z":["03060","03061","03062","03063","03064"],"lat":42.7715,"lng":-71.6263},{"n":"Nelson","c":"Cheshire","z":["03457"],"lat":42.8966,"lng":-72.0917},{"n":"New Boston","c":"Hillsborough","z":["03070"],"lat":42.9035,"lng":-71.7759},{"n":"New Castle","c":"Rockingham","z":["03854"],"lat":43.0649,"lng":-70.7216},{"n":"New Durham","c":"Strafford","z":["03855"],"lat":43.4595,"lng":-71.1191},{"n":"New Hampton","c":"Belknap","z":["03256"],"lat":43.6033,"lng":-71.6347},{"n":"New Ipswich","c":"Hillsborough","z":["03071"],"lat":42.7629,"lng":-71.8452},{"n":"New London","c":"Merrimack","z":["03257"],"lat":43.3017,"lng":-71.7336},{"n":"Newbury","c":"Merrimack","z":["03255"],"lat":43.3217,"lng":-72.0118},{"n":"Newfields","c":"Rockingham","z":["03856"],"lat":43.0374,"lng":-70.9782},{"n":"Newmarket","c":"Rockingham","z":["03857"],"lat":42.979,"lng":-70.8916},{"n":"Newport","c":"Sullivan","z":["03773"],"lat":43.3905,"lng":-72.1997},{"n":"Newton","c":"Rockingham","z":["03858"],"lat":42.9371,"lng":-71.0069},{"n":"Newton Junction","c":"Rockingham","z":["03859"],"lat":42.8619,"lng":-71.04},{"n":"North Conway","c":"Carroll","z":["03860"],"lat":43.7846,"lng":-71.1026},{"n":"North Hampton","c":"Rockingham","z":["03862"],"lat":43.0003,"lng":-70.9139},{"n":"North Haverhill","c":"Grafton","z":["03774"],"lat":44.0778,"lng":-72.0146},{"n":"North Salem","c":"Rockingham","z":["03073"],"lat":43.0059,"lng":-71.0132},{"n":"North Sandwich","c":"Carroll","z":["03259"],"lat":43.8597,"lng":-71.3772},{"n":"North Stratford","c":"Coos","z":["03590"],"lat":44.6956,"lng":-71.3874},{"n":"North Sutton","c":"Merrimack","z":["03260"],"lat":43.3653,"lng":-71.9341},{"n":"North Walpole","c":"Cheshire","z":["03609"],"lat":43.138,"lng":-72.4072},{"n":"North Woodstock","c":"Grafton","z":["03262"],"lat":44.0354,"lng":-71.6863},{"n":"Northwood","c":"Rockingham","z":["03261"],"lat":43.2087,"lng":-71.2026},{"n":"Nottingham","c":"Rockingham","z":["03290"],"lat":43.1248,"lng":-71.1259},{"n":"Orford","c":"Grafton","z":["03777"],"lat":43.9273,"lng":-72.1099},{"n":"Ossipee","c":"Carroll","z":["03864"],"lat":43.6674,"lng":-71.1533},{"n":"Pelham","c":"Hillsborough","z":["03076"],"lat":42.7407,"lng":-71.3187},{"n":"Peterborough","c":"Hillsborough","z":["03458"],"lat":42.9564,"lng":-71.9372},{"n":"Piermont","c":"Grafton","z":["03779"],"lat":43.9483,"lng":-72.0621},{"n":"Pike","c":"Grafton","z":["03780"],"lat":43.9675,"lng":-71.8409},{"n":"Pittsburg","c":"Coos","z":["03592"],"lat":44.6956,"lng":-71.3874},{"n":"Pittsfield","c":"Merrimack","z":["03263"],"lat":43.2978,"lng":-71.3437},{"n":"Plainfield","c":"Sullivan","z":["03781"],"lat":43.433,"lng":-72.2826},{"n":"Plaistow","c":"Rockingham","z":["03865"],"lat":42.9378,"lng":-70.9262},{"n":"Plymouth","c":"Grafton","z":["03264"],"lat":43.7109,"lng":-71.694},{"n":"Portsmouth","c":"Rockingham","z":["03801","03802","03803","03804"],"lat":43.0092,"lng":-70.9507},{"n":"Raymond","c":"Rockingham","z":["03077"],"lat":43.0593,"lng":-71.2045},{"n":"Rindge","c":"Cheshire","z":["03461"],"lat":42.7651,"lng":-72.0091},{"n":"Rochester","c":"Strafford","z":["03839","03866","03867","03868"],"lat":43.31,"lng":-70.9983},{"n":"Rollinsford","c":"Strafford","z":["03805","03869"],"lat":43.2853,"lng":-70.9307},{"n":"Rumney","c":"Grafton","z":["03266"],"lat":43.7525,"lng":-71.7884},{"n":"Rye","c":"Rockingham","z":["03870"],"lat":43.0109,"lng":-70.7648},{"n":"Rye Beach","c":"Rockingham","z":["03871"],"lat":42.9806,"lng":-70.7719},{"n":"Salem","c":"Rockingham","z":["03079"],"lat":42.872,"lng":-71.1962},{"n":"Salisbury","c":"Merrimack","z":["03268"],"lat":43.3618,"lng":-71.5588},{"n":"Sanbornton","c":"Belknap","z":["03269"],"lat":43.5018,"lng":-71.5142},{"n":"Sanbornville","c":"Carroll","z":["03872"],"lat":43.5707,"lng":-71.0794},{"n":"Sandown","c":"Rockingham","z":["03873"],"lat":42.9227,"lng":-71.1743},{"n":"Seabrook","c":"Rockingham","z":["03874"],"lat":42.9644,"lng":-70.8199},{"n":"Silver Lake","c":"Carroll","z":["03875"],"lat":43.8553,"lng":-71.1762},{"n":"Somersworth","c":"Strafford","z":["03878"],"lat":43.2295,"lng":-70.9583},{"n":"South Acworth","c":"Sullivan","z":["03607"],"lat":43.3645,"lng":-72.194},{"n":"South Newbury","c":"Merrimack","z":["03272"],"lat":43.3103,"lng":-71.6629},{"n":"South Sutton","c":"Merrimack","z":["03273"],"lat":43.3042,"lng":-71.9289},{"n":"South Tamworth","c":"Carroll","z":["03883"],"lat":43.8839,"lng":-71.2577},{"n":"Spofford","c":"Cheshire","z":["03462"],"lat":42.8707,"lng":-72.2394},{"n":"Springfield","c":"Sullivan","z":["03284"],"lat":43.4938,"lng":-72.047},{"n":"Stinson Lake","c":"Grafton","z":["03274"],"lat":43.9675,"lng":-71.8409},{"n":"Stoddard","c":"Cheshire","z":["03464"],"lat":42.9548,"lng":-72.1025},{"n":"Strafford","c":"Strafford","z":["03884"],"lat":43.2569,"lng":-71.1719},{"n":"Stratham","c":"Rockingham","z":["03885"],"lat":43.0129,"lng":-70.8821},{"n":"Sullivan","c":"Cheshire","z":["03445"],"lat":42.9982,"lng":-72.2019},{"n":"Sunapee","c":"Sullivan","z":["03782"],"lat":43.4268,"lng":-72.1547},{"n":"Suncook","c":"Merrimack","z":["03275"],"lat":43.2864,"lng":-71.599},{"n":"Swanzey","c":"Cheshire","z":["03446"],"lat":42.8411,"lng":-72.3301},{"n":"Tamworth","c":"Carroll","z":["03886"],"lat":43.6475,"lng":-71.2778},{"n":"Temple","c":"Hillsborough","z":["03084"],"lat":42.8223,"lng":-71.861},{"n":"Tilton","c":"Belknap","z":["03276","03298","03299"],"lat":43.5361,"lng":-71.4917},{"n":"Troy","c":"Cheshire","z":["03465"],"lat":42.8436,"lng":-72.2798},{"n":"Twin Mountain","c":"Coos","z":["03595"],"lat":44.2689,"lng":-71.5471},{"n":"Union","c":"Carroll","z":["03887"],"lat":43.46,"lng":-71.0408},{"n":"Walpole","c":"Cheshire","z":["03608"],"lat":43.0722,"lng":-72.3901},{"n":"Warner","c":"Merrimack","z":["03278"],"lat":43.3109,"lng":-71.8423},{"n":"Warren","c":"Grafton","z":["03279"],"lat":43.9675,"lng":-71.8409},{"n":"Washington","c":"Sullivan","z":["03280"],"lat":43.1723,"lng":-72.1007},{"n":"Waterville Valley","c":"Grafton","z":["03215"],"lat":43.9302,"lng":-71.5341},{"n":"Weare","c":"Hillsborough","z":["03281"],"lat":43.0842,"lng":-71.7626},{"n":"Wentworth","c":"Grafton","z":["03282"],"lat":43.9675,"lng":-71.8409},{"n":"West Chesterfield","c":"Cheshire","z":["03466"],"lat":42.8584,"lng":-72.4322},{"n":"West Lebanon","c":"Grafton","z":["03784"],"lat":43.6444,"lng":-72.2348},{"n":"West Nottingham","c":"Rockingham","z":["03291"],"lat":43.1823,"lng":-71.1396},{"n":"West Ossipee","c":"Carroll","z":["03890"],"lat":43.8118,"lng":-71.1946},{"n":"West Peterborough","c":"Hillsborough","z":["03468"],"lat":42.8908,"lng":-71.9334},{"n":"West Stewartstown","c":"Coos","z":["03597"],"lat":44.6956,"lng":-71.3874},{"n":"West Swanzey","c":"Cheshire","z":["03469"],"lat":42.8734,"lng":-72.3151},{"n":"Westmoreland","c":"Cheshire","z":["03467"],"lat":42.9739,"lng":-72.4426},{"n":"Whitefield","c":"Coos","z":["03598"],"lat":44.3637,"lng":-71.6102},{"n":"Wilmot","c":"Merrimack","z":["03287"],"lat":43.4485,"lng":-71.9158},{"n":"Wilton","c":"Hillsborough","z":["03086"],"lat":42.894,"lng":-71.7302},{"n":"Winchester","c":"Cheshire","z":["03470"],"lat":42.8958,"lng":-72.2749},{"n":"Windham","c":"Rockingham","z":["03087"],"lat":42.8922,"lng":-71.234},{"n":"Winnisquam","c":"Belknap","z":["03289"],"lat":43.4964,"lng":-71.5197},{"n":"Wolfeboro","c":"Carroll","z":["03894"],"lat":43.6671,"lng":-71.1836},{"n":"Wolfeboro Falls","c":"Carroll","z":["03896"],"lat":43.5892,"lng":-71.2189},{"n":"Wonalancet","c":"Carroll","z":["03897"],"lat":43.8839,"lng":-71.2577},{"n":"Woodstock","c":"Grafton","z":["03293"],"lat":43.9675,"lng":-71.8409},{"n":"Woodsville","c":"Grafton","z":["03785"],"lat":43.9486,"lng":-72.0807}]}